[
    {
        "question": "객체지향 설계 원칙 중, 서브타입(상속받은 하위 클래스)은 어디에서나 자신의 기반타입(상위클래스)으로 교체할 수 있다는 원칙은 리스코프 치환 원칙이다.",
        "answer": "정답"
    },{
        "question": "소프트웨어 설계에서 자주 발생하는 문제에 대해 일반적이고 반복적인 해결 방법은 모듈 분해가 있다.",
        "answer": "오답",
        "desc": "디자인 패턴"
    },{
        "question": "입력되는 데이터를 컴퓨터의 프로세서가 처리하기 전에 미리 처리하여 프로세서가 처리하는 시간을 줄여주는 프로그램이나 하드웨어를 FEP(Front-End Processor)라고 한다.",
        "answer": "정답"
    },{
        "question": "객체 지향 개념 중 하나 이상의 유사한 객체들을 묶어 공통된 특성을 표현한 데이터 추상화를 객체(Object)라고 한다.",
        "answer": "오답",
        "desc": "클래스(Class)"
    },{
        "question": "클린 코드(Clean Code)의 추상화는 하위 클래스/메소드/함수를 통해 애플리케이션의 특성을 간략하게 나타내고, 상세 내용은 상위 클래스/메소드/함수에서 구현한다",
        "answer": "오답",
        "desc" : "상위 클래스는 프로그램 특성만 간략하게, 하위 클래스는 세부적 내용을 구현한다."
    },{
        "question": "단위 테스트에서 테스트의 대상이 되는 하위 모듈을 호출하고, 파라미터를 전달하는 가상의 모듈로 상향식 테스트에 필요한 것은 테스트 드라이버(Test Driver)이다.",
        "answer": "정답"
    },{
        "question": "프트웨어 재공학의 주요 활동 중 기존 소프트웨어 시스템을 새로운 기술 또는 하드웨어 환경에서 사용할 수 있도록 변환하는 작업을 Migration이라고 한다.",
        "answer": "정답"
    },{
        "question": "아주 오래되거나 참고문서 또는 개발자가 없어 유지보수 작업이 아주 어려운 프로그램을 Alien Code라고 한다.",
        "answer": "정답"
    },{
        "question": "선형 구조에는 스택, 큐, 데크, 선형 리스트, 연결 리스트, 트리가 있다.",
        "answer": "오답",
        "desc": "선형 구조에는 스택, 큐, 데크, 선형 리스트, 연결 리스트, 비선형 구조에는 트리와 그래프, 파일 구조에는 순차파일, 색인파일, 직접파일 등이 있다."
    },{
        "question": "분할 정복(Divide and Conquer)에 기반한 알고리즘으로 피벗(pivot)을 사용하며 최악의 경우 n(n-1)/2 회의비교를 수행해야 하는 정렬(Sort)은 쉘(Shell) 정렬이다.",
        "answer": "오답",
        "desc": "퀵(Quick) 정렬"
    },{
        "question": "검토회의 전에 요구사항 명세서를 미리 배포하여 사전 검토한 후 짧은 검토 회의를 통해 오류를 조기에 검출하는데 목적을 두는 요구사항 검토 방법을 워크 스루라고 한다.",
        "answer": "정답"
    },{
        "question": "요구사항 검토 중 워크스루는 짧게는 일주인 길게는 한 달 동안 요구사항을 확인하여 결함을 발견하는 방법이다.",
        "answer": "오답",
        "desc": "워크스루 : 미리배포, 사전검토"
    },{
        "question": "프로젝트에 내재된 위험 요소를 인식하고 그 영향을 분석하여 이를 관리하는 활동으로서, 프로젝트를 성공시키기 위하여 위험 요소를 사전에 예측, 대비하는 모든 기술과 활동을 포함하는 것을 Risk Analysis라고 한다.",
        "answer": "정답"
    },{
        "question": "",
        "answer": ""
    },{
        "question": "",
        "answer": ""
    },{
        "question": "",
        "answer": ""
    },{
        "question": "",
        "answer": ""
    },{
        "question": "",
        "answer": ""
    },{
        "question": "",
        "answer": ""
    },{
        "question": "",
        "answer": ""
    },{
        "question": "",
        "answer": ""
    }
]